{
  "_class": "symbolInstance",
  "do_objectID": "B04730F2-940D-4638-9C83-BDFBBDAA133E",
  "exportOptions": {
    "_class": "exportOptions",
    "do_objectID": "E9CAFA95-C64A-4C00-8EB2-39927CA2E0AD",
    "exportFormats": [
    ],
    "includedLayerIds": [
    ],
    "layerOptions": 0,
    "shouldTrim": false
  },
  "frame": {
    "_class": "rect",
    "constrainProportions": false,
    "do_objectID": "D33037A4-E6A8-4EC7-AFA5-2849160D5502",
    "height": 410,
    "width": 61,
    "x": 350,
    "y": 551
  },
  "horizontalSpacing": 0,
  "isFlippedHorizontal": false,
  "isFlippedVertical": false,
  "isLocked": false,
  "isVisible": true,
  "layerListExpandedType": 0,
  "name": "bracket / right",
  "nameIsFixed": false,
  "overrideValues": [
  ],
  "resizingConstraint": 63,
  "resizingType": 0,
  "rotation": 0,
  "scale": 1,
  "shouldBreakMaskChain": false,
  "style": {
    "_class": "style",
    "do_objectID": "4883F14B-EF5E-48D9-B2EC-0EC57A8A1DE2",
    "endDecorationType": 0,
    "miterLimit": 10,
    "startDecorationType": 0
  },
  "symbolID": "5D87EC54-7B3E-4EBE-9F2D-B742909CA1E3",
  "verticalSpacing": 0
}